dash/__init__.py
dash/admin.py
dash/base.py
dash/clipboard.py
dash/conf.py
dash/constants.py
dash/decorators.py
dash/defaults.py
dash/discover.py
dash/exceptions.py
dash/factory.py
dash/fields.py
dash/forms.py
dash/helpers.py
dash/models.py
dash/settings.py
dash/urls.py
dash/utils.py
dash/views.py
dash/widgets.py
dash/contrib/__init__.py
dash/contrib/apps/__init__.py
dash/contrib/apps/public_dashboard/__init__.py
dash/contrib/apps/public_dashboard/apps.py
dash/contrib/apps/public_dashboard/urls.py
dash/contrib/apps/public_dashboard/views.py
dash/contrib/apps/public_dashboard/templates/public_dashboard/public_dashboard.html
dash/contrib/layouts/__init__.py
dash/contrib/layouts/android/__init__.py
dash/contrib/layouts/android/apps.py
dash/contrib/layouts/android/dash_layouts.py
dash/contrib/layouts/android/dash_plugins.py
dash/contrib/layouts/android/dash_widgets.py
dash/contrib/layouts/android/static/android/css/dash_layout_android.css
dash/contrib/layouts/android/static/android/css/dash_plugin_bookmark_android.css
dash/contrib/layouts/android/static/android/css/dash_plugin_url_android.css
dash/contrib/layouts/android/static/android/js/dash_layout_android.js
dash/contrib/layouts/android/templates/android/edit_layout.html
dash/contrib/layouts/android/templates/android/view_layout.html
dash/contrib/layouts/bootstrap2/__init__.py
dash/contrib/layouts/bootstrap2/apps.py
dash/contrib/layouts/bootstrap2/conf.py
dash/contrib/layouts/bootstrap2/dash_layouts.py
dash/contrib/layouts/bootstrap2/dash_plugins.py
dash/contrib/layouts/bootstrap2/dash_widgets.py
dash/contrib/layouts/bootstrap2/defaults.py
dash/contrib/layouts/bootstrap2/forms.py
dash/contrib/layouts/bootstrap2/settings.py
dash/contrib/layouts/bootstrap2/static/bootstrap2/css/bootstrap-responsive.css
dash/contrib/layouts/bootstrap2/static/bootstrap2/css/bootstrap-responsive.min.css
dash/contrib/layouts/bootstrap2/static/bootstrap2/css/bootstrap.css
django_dash-0.6.1.dist-info/LICENSES.rst
django_dash-0.6.1.dist-info/LICENSE_GPL2.0.txt
django_dash-0.6.1.dist-info/LICENSE_LGPL_2.1.txt
django_dash-0.6.1.dist-info/METADATA
django_dash-0.6.1.dist-info/WHEEL
django_dash-0.6.1.dist-info/top_level.txt
django_dash-0.6.1.dist-info/RECORD
