Metadata-Version: 1.2
Name: django-dash
Version: 0.6.1
Summary: Customisable, modular dashboard application framework for Django.
Home-page: https://github.com/barseghyanartur/django-dash/
Author: Artur Barseghyan
Author-email: artur.barseghyan@gmail.com
License: GPL-2.0-only OR LGPL-2.1-or-later
Project-URL: Bug Tracker, https://github.com/barseghyanartur/django-dash/issues
Project-URL: Documentation, https://django-dash.readthedocs.io/
Project-URL: Source Code, https://github.com/barseghyanartur/django-dash
Project-URL: Changelog, https://django-dash.readthedocs.io/en/latest/changelog.html
Keywords: dashboard,django,django dashboard
Platform: UNKNOWN
Classifier: Programming Language :: Python :: 3
Classifier: Programming Language :: Python :: 3.6
Classifier: Programming Language :: Python :: 3.7
Classifier: Programming Language :: Python :: 3.8
Classifier: Programming Language :: Python :: 3.9
Classifier: Environment :: Web Environment
Classifier: License :: OSI Approved :: GNU General Public License v2 (GPLv2)
Classifier: License :: OSI Approved :: GNU Lesser General Public License v2 or later (LGPLv2+)
Classifier: Framework :: Django
Classifier: Intended Audience :: Developers
Classifier: Operating System :: OS Independent
Classifier: Development Status :: 4 - Beta
